ggc_list/__init__.py
ggc_list-1.1.1.dist-info/LICENSE
ggc_list-1.1.1.dist-info/METADATA
ggc_list-1.1.1.dist-info/WHEEL
ggc_list-1.1.1.dist-info/top_level.txt
ggc_list-1.1.1.dist-info/RECORD
