Metadata-Version: 2.1
Name: ggc-list
Version: 1.1.1
Summary: A small example package
Home-page: UNKNOWN
Author: Will Gao
Author-email: myworld88ggc@gmail.com
License: UNKNOWN
Platform: UNKNOWN
Classifier: Programming Language :: Python :: 3
Classifier: License :: OSI Approved :: MIT License
Classifier: Operating System :: OS Independent
